oauth_jaccount/__init__.py
oauth_jaccount/client.py
oauth_jaccount-0.1.5.dist-info/LICENSE
oauth_jaccount-0.1.5.dist-info/METADATA
oauth_jaccount-0.1.5.dist-info/WHEEL
oauth_jaccount-0.1.5.dist-info/top_level.txt
oauth_jaccount-0.1.5.dist-info/RECORD
