Metadata-Version: 2.1
Name: oauth-jaccount
Version: 0.1.5
Summary: python package for jaccount oauth
Home-page: https://github.com/tc-imba/python-oauth-jaccount
Author: tc-imba
Author-email: liuyh615@126.com
License: UNKNOWN
Platform: UNKNOWN
Classifier: Programming Language :: Python :: 3
Classifier: License :: OSI Approved :: MIT License
Classifier: Operating System :: OS Independent
Requires-Python: >=3
License-File: LICENSE
Requires-Dist: oauthlib
Requires-Dist: PyJWT
